LICENSE
MANIFEST.in
README.md
pyproject.toml
setup.cfg
setup.py
ccnasr.egg-info/PKG-INFO
ccnasr.egg-info/SOURCES.txt
ccnasr.egg-info/dependency_links.txt
ccnasr.egg-info/entry_points.txt
ccnasr.egg-info/requires.txt
ccnasr.egg-info/top_level.txt
nasr/__init__.py
nasr/__main__.py
nasr/bisector.py
nasr/cli.py
nasr/compilerstore.py
nasr/defaults.py
nasr/py.typed
nasr/builder/__init__.py
nasr/builder/builder.py
nasr/data/patches/gcc/0001-c-Implement-P1467R9-Extended-floating-point-types-an
nasr/data/patches/gcc/0001-check_size_and_offset.patch
nasr/data/patches/gcc/0001-fixinc-don-t-fix-machine-names-in-__has_include-.-PR
nasr/data/patches/gcc/0001-linux-fs.patch
nasr/data/patches/gcc/0001-malloc-attribute.patch
nasr/data/patches/gcc/0001-malloc-attributes-patch.patch
nasr/data/patches/gcc/gcc-fix-simple-object-decl-and-use-in-gcc-lto.patch
nasr/data/patches/gcc/gcc-libsanitizer.sh
nasr/data/patches/gcc/gcc-simple-object-declaration.patch
nasr/data/patches/gcc/gcc-ustat.patch
nasr/data/patches/llvm/0001-uintptr_t-patch.patch
nasr/data/patches/llvm/llvm-GCOpenMPRuntime.cpp-lambda-issues.patch
nasr/data/patches/llvm/llvm-MicrosoftDemangleNodes-missing-includes.patch
nasr/data/patches/llvm/llvm-MicrosoftDemangleNodes.h-fix-includes.patch
nasr/utils/__init__.py
nasr/utils/utils.py