Metadata-Version: 2.2
Name: ccnasr
Version: 0.1.2
Summary: Simple
Home-page: https://github.com/DeadCodeProductions/nasr
Author: Nasr
Author-email: nasr2python@gmail.com
License: Apache License 2.0
Classifier: Programming Language :: Python :: 3
Classifier: License :: OSI Approved :: MIT License
Classifier: Operating System :: OS Independent
Requires-Python: >=3.10
License-File: LICENSE
Requires-Dist: diopter>=0.0.24
Dynamic: author
Dynamic: author-email
Dynamic: classifier
Dynamic: summary
